<?xml version="1.0" encoding="UTF-8"?><database>
    <element attributes="enforce_dot_walk_cross_scope_access=true" db_object_id="6f7g8h9i0j1k2l3m4n5o6p7q8r9s0t1u" label="Role Capability Map" max_length="0" name="u_role_capability_map" type="collection">
        <element choice="3" display="true" dynamic_ref_qual="sys_idIN0a6613e4c37c0390f6ebf8dd" label="Capability" mandatory="true" max_length="32" name="capability" reference="u_idp_capability" type="reference">
            <choice/>
        </element>
        <element choice="3" display="true" dynamic_ref_qual="sys_idINx_146833_idpkiroq.app_de" label="Role" mandatory="true" max_length="32" name="role" reference="sys_user_role" type="reference">
            <choice/>
        </element>
        <index name="index">
            <element name="capability"/>
        </index>
        <index name="index2">
            <element name="role"/>
        </index>
    </element>
</database>
